imad213/__init__.py
imad213/imad.py
imad213-2.2.dist-info/METADATA
imad213-2.2.dist-info/WHEEL
imad213-2.2.dist-info/entry_points.txt
imad213-2.2.dist-info/top_level.txt
imad213-2.2.dist-info/RECORD
