Metadata-Version: 2.4
Name: imad213
Version: 2.2
Requires-Dist: requests
Requires-Dist: beautifulsoup4
Dynamic: description
Dynamic: description-content-type
Dynamic: requires-dist
